package_example/__init__.py
package_example/functions.py
package_example-0.1.dist-info/DESCRIPTION.rst
package_example-0.1.dist-info/METADATA
package_example-0.1.dist-info/RECORD
package_example-0.1.dist-info/WHEEL
package_example-0.1.dist-info/metadata.json
package_example-0.1.dist-info/top_level.txt
