Metadata-Version: 2.0
Name: package-example
Version: 0.1
Summary: The funniest joke in the world
Home-page: http://github.com/storborg/funniest
Author: ASPP2017
Author-email: aspp@example.com
License: MIT
Platform: UNKNOWN
